<?xml version="1.0" encoding="utf-8" standalone="yes"?>
<Template xmlns:element="http://webmill.riverock.org/xsd/riverock-template-page-elements.xsd">
    <element:custom value="HeaderStart"/>
    <element:custom value="HeaderText"/>
    <element:custom value="HeaderEnd"/>
    <element:portlet xmlRoot="TopMenu" value="mill.menu" code="TOP"/>
    <element:portlet xmlRoot="LoginOnIndexPage" value="mill.login_xml"/>
    <element:custom value="MainStart"/>
    <element:portlet value="mill.menu" code="MAIN"/>
    <element:custom value="Separator"/>
    <element:custom value="Footer"/>
</Template>
